mcp_text_editor/__init__.py
mcp_text_editor/models.py
mcp_text_editor/schema_compat.py
mcp_text_editor/server.py
mcp_text_editor/service.py
mcp_text_editor/text_editor.py
mcp_text_editor/utils.py
mcp_text_editor/version.py
mcp_text_editor/handlers/__init__.py
mcp_text_editor/handlers/append_text_file_contents.py
mcp_text_editor/handlers/base.py
mcp_text_editor/handlers/create_text_file.py
mcp_text_editor/handlers/delete_text_file_contents.py
mcp_text_editor/handlers/get_text_file_contents.py
mcp_text_editor/handlers/insert_text_file_contents.py
mcp_text_editor/handlers/patch_text_file_contents.py
mcp_text_editor-1.2.0.dist-info/METADATA
mcp_text_editor-1.2.0.dist-info/WHEEL
mcp_text_editor-1.2.0.dist-info/entry_points.txt
mcp_text_editor-1.2.0.dist-info/licenses/LICENSE
mcp_text_editor-1.2.0.dist-info/RECORD
