Metadata-Version: 2.4
Name: mcp-text-editor
Version: 1.2.0
Summary: MCP Text Editor Server - Edit text files via MCP protocol
Author: tumf
License: MIT
License-File: LICENSE
Requires-Python: >=3.13
Requires-Dist: chardet>=5.2.0
Requires-Dist: mcp>=1.25.0
Provides-Extra: dev
Requires-Dist: black>=25.0.0; extra == 'dev'
Requires-Dist: isort>=6.0.0; extra == 'dev'
Requires-Dist: mypy>=1.19.0; extra == 'dev'
Requires-Dist: pre-commit>=4.5.0; extra == 'dev'
Requires-Dist: ruff>=0.14.0; extra == 'dev'
Provides-Extra: test
Requires-Dist: pytest-asyncio>=1.3.0; extra == 'test'
Requires-Dist: pytest-cov>=7.0.0; extra == 'test'
Requires-Dist: pytest-env>=1.2.0; extra == 'test'
Requires-Dist: pytest-mock>=3.15.0; extra == 'test'
Requires-Dist: pytest>=9.0.0; extra == 'test'
